pg_helpers/__init__.py
pg_helpers/config.py
pg_helpers/database.py
pg_helpers/notifications.py
pg_helpers/query_utils.py
pg_helpers-1.3.3.dist-info/licenses/LICENSE
tests/__init__.py
tests/test_database.py
pg_helpers-1.3.3.dist-info/METADATA
pg_helpers-1.3.3.dist-info/WHEEL
pg_helpers-1.3.3.dist-info/top_level.txt
pg_helpers-1.3.3.dist-info/RECORD
