Metadata-Version: 2.4
Name: pg-helpers
Version: 1.3.3
Summary: PostgreSQL helper functions for data analysis with enterprise-grade security
Home-page: https://github.com/lenwood/pg_helpers
Author: Chris Leonard
Author-email: lenwood@duck.com
Project-URL: Bug Reports, https://github.com/lenwood/pg_helpers/issues
Project-URL: Source, https://github.com/lenwood/pg_helpers
Project-URL: Documentation, https://github.com/lenwood/pg_helpers#readme
Keywords: postgresql,postgres,database,sql,pandas,data-analysis,ssl,security,retry-logic,sqlalchemy,data-science
Classifier: Development Status :: 4 - Beta
Classifier: Intended Audience :: Developers
Classifier: Intended Audience :: Science/Research
Classifier: Intended Audience :: Financial and Insurance Industry
Classifier: Topic :: Database
Classifier: Topic :: Scientific/Engineering
Classifier: Topic :: Software Development :: Libraries :: Python Modules
Classifier: License :: OSI Approved :: MIT License
Classifier: Operating System :: OS Independent
Classifier: Programming Language :: Python :: 3
Classifier: Programming Language :: Python :: 3.8
Classifier: Programming Language :: Python :: 3.9
Classifier: Programming Language :: Python :: 3.10
Classifier: Programming Language :: Python :: 3.11
Classifier: Programming Language :: Python :: 3.12
Classifier: Environment :: Console
Classifier: Natural Language :: English
Requires-Python: >=3.8
License-File: LICENSE
Requires-Dist: pandas>=1.3.0
Requires-Dist: psycopg2-binary>=2.9.0
Requires-Dist: sqlalchemy>=1.4.0
Requires-Dist: python-dotenv>=0.19.0
Provides-Extra: test
Requires-Dist: pytest>=6.0; extra == "test"
Requires-Dist: pytest-cov>=2.10.0; extra == "test"
Requires-Dist: coverage>=5.0; extra == "test"
Provides-Extra: dev
Requires-Dist: pytest>=6.0; extra == "dev"
Requires-Dist: pytest-cov>=2.10.0; extra == "dev"
Requires-Dist: coverage>=5.0; extra == "dev"
Requires-Dist: flake8>=3.8.0; extra == "dev"
Requires-Dist: black>=21.0.0; extra == "dev"
Requires-Dist: tox>=3.20.0; extra == "dev"
Provides-Extra: windows
Requires-Dist: winsound; extra == "windows"
Dynamic: author
Dynamic: author-email
Dynamic: classifier
Dynamic: description
Dynamic: description-content-type
Dynamic: home-page
Dynamic: keywords
Dynamic: license-file
Dynamic: project-url
Dynamic: provides-extra
Dynamic: requires-dist
Dynamic: requires-python
Dynamic: summary
